nhm_spider/__init__.py
nhm_spider/crawler.py
nhm_spider/exceptions.py
nhm_spider/common/__init__.py
nhm_spider/common/log.py
nhm_spider/common/time_counter.py
nhm_spider/core/__init__.py
nhm_spider/core/downloader.py
nhm_spider/core/engine.py
nhm_spider/core/scheduler.py
nhm_spider/download_middleware/__init__.py
nhm_spider/download_middleware/base.py
nhm_spider/download_middleware/default_headers.py
nhm_spider/download_middleware/interface.py
nhm_spider/download_middleware/manager.py
nhm_spider/download_middleware/retry.py
nhm_spider/download_middleware/timeout.py
nhm_spider/http/__init__.py
nhm_spider/http/headers.py
nhm_spider/http/request.py
nhm_spider/http/response.py
nhm_spider/item/__init__.py
nhm_spider/pipeline/__init__.py
nhm_spider/pipeline/base.py
nhm_spider/pipeline/interface.py
nhm_spider/settings/__init__.py
nhm_spider/settings/default_settings.py
nhm_spider/settings/settings_manager.py
nhm_spider/spider/__init__.py
nhm_spider/spider/base.py
nhm_spider/spider/interface.py
nhm_spider/spider_middleware/__init__.py
nhm_spider/test/__init__.py
nhm_spider/test/demo.py
nhm_spider/test/test.py
nhm_spider/test/test1.py
nhm_spider/test/settings/__init__.py
nhm_spider/test/settings/settings_manager.py
nhm_spider/utils/__init__.py
nhm_spider/utils/date.py
nhm_spider/utils/pqueue.py
nhm_spider/utils/project.py
nhm_spider/utils/request.py
nhm_spider/utils/signal.py
nhm_spider-2.0.1.dist-info/METADATA
nhm_spider-2.0.1.dist-info/WHEEL
nhm_spider-2.0.1.dist-info/top_level.txt
nhm_spider-2.0.1.dist-info/RECORD
