Metadata-Version: 2.1
Name: nhm-spider
Version: 2.0.1
Summary: base on asyncio, spider module like scrapy.
Home-page: https://github.com/noHairMan/nhm-spider
Author: noHairMan
Author-email: zongxuheng@163.com
License: UNKNOWN
Platform: UNKNOWN
Classifier: Programming Language :: Python :: 3
Classifier: License :: OSI Approved :: MIT License
Classifier: Operating System :: OS Independent
Requires-Python: >=3.9
Requires-Dist: aiohttp
